kandinsky_lib/__init__.py
kandinsky_lib/kandinsky.py
kandinsky_lib/start.py
tests/__init__.py
tests/kandinskytest.py
kandinsky_simple_lib-0.1.3.dist-info/METADATA
kandinsky_simple_lib-0.1.3.dist-info/WHEEL
kandinsky_simple_lib-0.1.3.dist-info/top_level.txt
kandinsky_simple_lib-0.1.3.dist-info/RECORD
