Metadata-Version: 2.1
Name: kandinsky-simple-lib
Version: 0.1.3
Summary: Простая библиотека для работы с нейросетью Kandinsky
Home-page: https://github.com/swiftmessage/kandinsky-simple-lib
Author: SwiftMessage
Author-email: support@swiftmessage.org
Classifier: Programming Language :: Python :: 3
Classifier: License :: OSI Approved :: MIT License
Classifier: Operating System :: OS Independent
Requires-Python: >=3.6
Requires-Dist: requests>=2.32.3
Requires-Dist: pillow>=11.0.0
